{
  "data": {
    "version": 1,
    "directus": "11.15.4",
    "vendor": "postgres",
    "collections": [
      {
        "collection": "chiusella",
        "meta": {
          "accountability": "all",
          "archive_app_filter": true,
          "archive_field": null,
          "archive_value": null,
          "collapse": "open",
          "collection": "chiusella",
          "color": null,
          "display_template": null,
          "group": null,
          "hidden": false,
          "icon": null,
          "item_duplication_fields": null,
          "note": null,
          "preview_url": null,
          "singleton": true,
          "sort": 1,
          "sort_field": null,
          "translations": null,
          "unarchive_value": null,
          "versioning": false
        },
        "schema": {
          "name": "chiusella"
        }
      },
      {
        "collection": "chiusella_apartments",
        "meta": {
          "accountability": "all",
          "archive_app_filter": true,
          "archive_field": null,
          "archive_value": null,
          "collapse": "open",
          "collection": "chiusella_apartments",
          "color": null,
          "display_template": null,
          "group": "chiusella",
          "hidden": false,
          "icon": null,
          "item_duplication_fields": null,
          "note": null,
          "preview_url": null,
          "singleton": false,
          "sort": 1,
          "sort_field": null,
          "translations": null,
          "unarchive_value": null,
          "versioning": false
        },
        "schema": {
          "name": "chiusella_apartments"
        }
      },
      {
        "collection": "chiusella_experiences",
        "meta": {
          "accountability": "all",
          "archive_app_filter": true,
          "archive_field": null,
          "archive_value": null,
          "collapse": "open",
          "collection": "chiusella_experiences",
          "color": null,
          "display_template": null,
          "group": "chiusella",
          "hidden": false,
          "icon": null,
          "item_duplication_fields": null,
          "note": null,
          "preview_url": null,
          "singleton": false,
          "sort": 2,
          "sort_field": null,
          "translations": null,
          "unarchive_value": null,
          "versioning": false
        },
        "schema": {
          "name": "chiusella_experiences"
        }
      },
      {
        "collection": "chiusella_services",
        "meta": {
          "accountability": "all",
          "archive_app_filter": true,
          "archive_field": null,
          "archive_value": null,
          "collapse": "open",
          "collection": "chiusella_services",
          "color": null,
          "display_template": null,
          "group": "chiusella",
          "hidden": false,
          "icon": null,
          "item_duplication_fields": null,
          "note": null,
          "preview_url": null,
          "singleton": false,
          "sort": 3,
          "sort_field": null,
          "translations": null,
          "unarchive_value": null,
          "versioning": false
        },
        "schema": {
          "name": "chiusella_services"
        }
      }
    ],
    "fields": [
      {
        "collection": "chiusella",
        "field": "id",
        "type": "uuid",
        "meta": {
          "collection": "chiusella",
          "conditions": null,
          "display": null,
          "display_options": null,
          "field": "id",
          "group": null,
          "hidden": true,
          "interface": "input",
          "note": null,
          "options": null,
          "readonly": true,
          "required": false,
          "searchable": true,
          "sort": 1,
          "special": [
            "uuid"
          ],
          "translations": null,
          "validation": null,
          "validation_message": null,
          "width": "full"
        },
        "schema": {
          "name": "id",
          "table": "chiusella",
          "data_type": "uuid",
          "default_value": null,
          "max_length": null,
          "numeric_precision": null,
          "numeric_scale": null,
          "is_nullable": false,
          "is_unique": true,
          "is_indexed": false,
          "is_primary_key": true,
          "is_generated": false,
          "generation_expression": null,
          "has_auto_increment": false,
          "foreign_key_table": null,
          "foreign_key_column": null
        }
      },
      {
        "collection": "chiusella",
        "field": "property_name",
        "type": "string",
        "meta": {
          "collection": "chiusella",
          "conditions": null,
          "display": null,
          "display_options": null,
          "field": "property_name",
          "group": null,
          "hidden": false,
          "interface": "input",
          "note": null,
          "options": null,
          "readonly": false,
          "required": false,
          "searchable": true,
          "sort": 2,
          "special": null,
          "translations": null,
          "validation": null,
          "validation_message": null,
          "width": "full"
        },
        "schema": {
          "name": "property_name",
          "table": "chiusella",
          "data_type": "character varying",
          "default_value": null,
          "max_length": 255,
          "numeric_precision": null,
          "numeric_scale": null,
          "is_nullable": true,
          "is_unique": false,
          "is_indexed": false,
          "is_primary_key": false,
          "is_generated": false,
          "generation_expression": null,
          "has_auto_increment": false,
          "foreign_key_table": null,
          "foreign_key_column": null
        }
      },
      {
        "collection": "chiusella",
        "field": "property_type",
        "type": "string",
        "meta": {
          "collection": "chiusella",
          "conditions": null,
          "display": null,
          "display_options": null,
          "field": "property_type",
          "group": null,
          "hidden": false,
          "interface": "input",
          "note": null,
          "options": null,
          "readonly": false,
          "required": false,
          "searchable": true,
          "sort": 3,
          "special": null,
          "translations": null,
          "validation": null,
          "validation_message": null,
          "width": "full"
        },
        "schema": {
          "name": "property_type",
          "table": "chiusella",
          "data_type": "character varying",
          "default_value": null,
          "max_length": 255,
          "numeric_precision": null,
          "numeric_scale": null,
          "is_nullable": true,
          "is_unique": false,
          "is_indexed": false,
          "is_primary_key": false,
          "is_generated": false,
          "generation_expression": null,
          "has_auto_increment": false,
          "foreign_key_table": null,
          "foreign_key_column": null
        }
      },
      {
        "collection": "chiusella",
        "field": "property_description",
        "type": "text",
        "meta": {
          "collection": "chiusella",
          "conditions": null,
          "display": null,
          "display_options": null,
          "field": "property_description",
          "group": null,
          "hidden": false,
          "interface": "input-rich-text-html",
          "note": null,
          "options": null,
          "readonly": false,
          "required": false,
          "searchable": true,
          "sort": 4,
          "special": null,
          "translations": null,
          "validation": null,
          "validation_message": null,
          "width": "full"
        },
        "schema": {
          "name": "property_description",
          "table": "chiusella",
          "data_type": "text",
          "default_value": null,
          "max_length": null,
          "numeric_precision": null,
          "numeric_scale": null,
          "is_nullable": true,
          "is_unique": false,
          "is_indexed": false,
          "is_primary_key": false,
          "is_generated": false,
          "generation_expression": null,
          "has_auto_increment": false,
          "foreign_key_table": null,
          "foreign_key_column": null
        }
      },
      {
        "collection": "chiusella",
        "field": "property_history",
        "type": "text",
        "meta": {
          "collection": "chiusella",
          "conditions": null,
          "display": null,
          "display_options": null,
          "field": "property_history",
          "group": null,
          "hidden": false,
          "interface": "input-rich-text-html",
          "note": null,
          "options": null,
          "readonly": false,
          "required": false,
          "searchable": true,
          "sort": 5,
          "special": null,
          "translations": null,
          "validation": null,
          "validation_message": null,
          "width": "full"
        },
        "schema": {
          "name": "property_history",
          "table": "chiusella",
          "data_type": "text",
          "default_value": null,
          "max_length": null,
          "numeric_precision": null,
          "numeric_scale": null,
          "is_nullable": true,
          "is_unique": false,
          "is_indexed": false,
          "is_primary_key": false,
          "is_generated": false,
          "generation_expression": null,
          "has_auto_increment": false,
          "foreign_key_table": null,
          "foreign_key_column": null
        }
      },
      {
        "collection": "chiusella",
        "field": "property_location_description",
        "type": "text",
        "meta": {
          "collection": "chiusella",
          "conditions": null,
          "display": null,
          "display_options": null,
          "field": "property_location_description",
          "group": null,
          "hidden": false,
          "interface": "input-rich-text-html",
          "note": null,
          "options": null,
          "readonly": false,
          "required": false,
          "searchable": true,
          "sort": 6,
          "special": null,
          "translations": null,
          "validation": null,
          "validation_message": null,
          "width": "full"
        },
        "schema": {
          "name": "property_location_description",
          "table": "chiusella",
          "data_type": "text",
          "default_value": null,
          "max_length": null,
          "numeric_precision": null,
          "numeric_scale": null,
          "is_nullable": true,
          "is_unique": false,
          "is_indexed": false,
          "is_primary_key": false,
          "is_generated": false,
          "generation_expression": null,
          "has_auto_increment": false,
          "foreign_key_table": null,
          "foreign_key_column": null
        }
      },
      {
        "collection": "chiusella",
        "field": "property_town",
        "type": "string",
        "meta": {
          "collection": "chiusella",
          "conditions": null,
          "display": null,
          "display_options": null,
          "field": "property_town",
          "group": null,
          "hidden": false,
          "interface": "input",
          "note": null,
          "options": null,
          "readonly": false,
          "required": false,
          "searchable": true,
          "sort": 7,
          "special": null,
          "translations": null,
          "validation": null,
          "validation_message": null,
          "width": "full"
        },
        "schema": {
          "name": "property_town",
          "table": "chiusella",
          "data_type": "character varying",
          "default_value": null,
          "max_length": 255,
          "numeric_precision": null,
          "numeric_scale": null,
          "is_nullable": true,
          "is_unique": false,
          "is_indexed": false,
          "is_primary_key": false,
          "is_generated": false,
          "generation_expression": null,
          "has_auto_increment": false,
          "foreign_key_table": null,
          "foreign_key_column": null
        }
      },
      {
        "collection": "chiusella",
        "field": "property_region",
        "type": "string",
        "meta": {
          "collection": "chiusella",
          "conditions": null,
          "display": null,
          "display_options": null,
          "field": "property_region",
          "group": null,
          "hidden": false,
          "interface": "input",
          "note": null,
          "options": null,
          "readonly": false,
          "required": false,
          "searchable": true,
          "sort": 8,
          "special": null,
          "translations": null,
          "validation": null,
          "validation_message": null,
          "width": "full"
        },
        "schema": {
          "name": "property_region",
          "table": "chiusella",
          "data_type": "character varying",
          "default_value": null,
          "max_length": 255,
          "numeric_precision": null,
          "numeric_scale": null,
          "is_nullable": true,
          "is_unique": false,
          "is_indexed": false,
          "is_primary_key": false,
          "is_generated": false,
          "generation_expression": null,
          "has_auto_increment": false,
          "foreign_key_table": null,
          "foreign_key_column": null
        }
      },
      {
        "collection": "chiusella",
        "field": "property_website",
        "type": "string",
        "meta": {
          "collection": "chiusella",
          "conditions": null,
          "display": null,
          "display_options": null,
          "field": "property_website",
          "group": null,
          "hidden": false,
          "interface": "input",
          "note": null,
          "options": null,
          "readonly": false,
          "required": false,
          "searchable": true,
          "sort": 9,
          "special": null,
          "translations": null,
          "validation": null,
          "validation_message": null,
          "width": "full"
        },
        "schema": {
          "name": "property_website",
          "table": "chiusella",
          "data_type": "character varying",
          "default_value": null,
          "max_length": 255,
          "numeric_precision": null,
          "numeric_scale": null,
          "is_nullable": true,
          "is_unique": false,
          "is_indexed": false,
          "is_primary_key": false,
          "is_generated": false,
          "generation_expression": null,
          "has_auto_increment": false,
          "foreign_key_table": null,
          "foreign_key_column": null
        }
      },
      {
        "collection": "chiusella",
        "field": "property_total_apartments",
        "type": "integer",
        "meta": {
          "collection": "chiusella",
          "conditions": null,
          "display": null,
          "display_options": null,
          "field": "property_total_apartments",
          "group": null,
          "hidden": false,
          "interface": "input",
          "note": null,
          "options": null,
          "readonly": false,
          "required": false,
          "searchable": true,
          "sort": 10,
          "special": null,
          "translations": null,
          "validation": null,
          "validation_message": null,
          "width": "full"
        },
        "schema": {
          "name": "property_total_apartments",
          "table": "chiusella",
          "data_type": "integer",
          "default_value": null,
          "max_length": null,
          "numeric_precision": 32,
          "numeric_scale": 0,
          "is_nullable": true,
          "is_unique": false,
          "is_indexed": false,
          "is_primary_key": false,
          "is_generated": false,
          "generation_expression": null,
          "has_auto_increment": false,
          "foreign_key_table": null,
          "foreign_key_column": null
        }
      },
      {
        "collection": "chiusella",
        "field": "property_capacity_range",
        "type": "string",
        "meta": {
          "collection": "chiusella",
          "conditions": null,
          "display": null,
          "display_options": null,
          "field": "property_capacity_range",
          "group": null,
          "hidden": false,
          "interface": "input",
          "note": null,
          "options": null,
          "readonly": false,
          "required": false,
          "searchable": true,
          "sort": 11,
          "special": null,
          "translations": null,
          "validation": null,
          "validation_message": null,
          "width": "full"
        },
        "schema": {
          "name": "property_capacity_range",
          "table": "chiusella",
          "data_type": "character varying",
          "default_value": null,
          "max_length": 255,
          "numeric_precision": null,
          "numeric_scale": null,
          "is_nullable": true,
          "is_unique": false,
          "is_indexed": false,
          "is_primary_key": false,
          "is_generated": false,
          "generation_expression": null,
          "has_auto_increment": false,
          "foreign_key_table": null,
          "foreign_key_column": null
        }
      },
      {
        "collection": "chiusella",
        "field": "property_furnishing_style",
        "type": "string",
        "meta": {
          "collection": "chiusella",
          "conditions": null,
          "display": null,
          "display_options": null,
          "field": "property_furnishing_style",
          "group": null,
          "hidden": false,
          "interface": "input",
          "note": null,
          "options": null,
          "readonly": false,
          "required": false,
          "searchable": true,
          "sort": 12,
          "special": null,
          "translations": null,
          "validation": null,
          "validation_message": null,
          "width": "full"
        },
        "schema": {
          "name": "property_furnishing_style",
          "table": "chiusella",
          "data_type": "character varying",
          "default_value": null,
          "max_length": 255,
          "numeric_precision": null,
          "numeric_scale": null,
          "is_nullable": true,
          "is_unique": false,
          "is_indexed": false,
          "is_primary_key": false,
          "is_generated": false,
          "generation_expression": null,
          "has_auto_increment": false,
          "foreign_key_table": null,
          "foreign_key_column": null
        }
      },
      {
        "collection": "chiusella",
        "field": "property_directions_from_north",
        "type": "text",
        "meta": {
          "collection": "chiusella",
          "conditions": null,
          "display": null,
          "display_options": null,
          "field": "property_directions_from_north",
          "group": null,
          "hidden": false,
          "interface": "input-rich-text-html",
          "note": null,
          "options": null,
          "readonly": false,
          "required": false,
          "searchable": true,
          "sort": 13,
          "special": null,
          "translations": null,
          "validation": null,
          "validation_message": null,
          "width": "full"
        },
        "schema": {
          "name": "property_directions_from_north",
          "table": "chiusella",
          "data_type": "text",
          "default_value": null,
          "max_length": null,
          "numeric_precision": null,
          "numeric_scale": null,
          "is_nullable": true,
          "is_unique": false,
          "is_indexed": false,
          "is_primary_key": false,
          "is_generated": false,
          "generation_expression": null,
          "has_auto_increment": false,
          "foreign_key_table": null,
          "foreign_key_column": null
        }
      },
      {
        "collection": "chiusella",
        "field": "property_directions_from_south",
        "type": "text",
        "meta": {
          "collection": "chiusella",
          "conditions": null,
          "display": null,
          "display_options": null,
          "field": "property_directions_from_south",
          "group": null,
          "hidden": false,
          "interface": "input-rich-text-html",
          "note": null,
          "options": null,
          "readonly": false,
          "required": false,
          "searchable": true,
          "sort": 14,
          "special": null,
          "translations": null,
          "validation": null,
          "validation_message": null,
          "width": "full"
        },
        "schema": {
          "name": "property_directions_from_south",
          "table": "chiusella",
          "data_type": "text",
          "default_value": null,
          "max_length": null,
          "numeric_precision": null,
          "numeric_scale": null,
          "is_nullable": true,
          "is_unique": false,
          "is_indexed": false,
          "is_primary_key": false,
          "is_generated": false,
          "generation_expression": null,
          "has_auto_increment": false,
          "foreign_key_table": null,
          "foreign_key_column": null
        }
      },
      {
        "collection": "chiusella",
        "field": "property_distances",
        "type": "string",
        "meta": {
          "collection": "chiusella",
          "conditions": null,
          "display": null,
          "display_options": null,
          "field": "property_distances",
          "group": null,
          "hidden": false,
          "interface": "input",
          "note": null,
          "options": null,
          "readonly": false,
          "required": false,
          "searchable": true,
          "sort": 15,
          "special": null,
          "translations": null,
          "validation": null,
          "validation_message": null,
          "width": "full"
        },
        "schema": {
          "name": "property_distances",
          "table": "chiusella",
          "data_type": "character varying",
          "default_value": null,
          "max_length": 255,
          "numeric_precision": null,
          "numeric_scale": null,
          "is_nullable": true,
          "is_unique": false,
          "is_indexed": false,
          "is_primary_key": false,
          "is_generated": false,
          "generation_expression": null,
          "has_auto_increment": false,
          "foreign_key_table": null,
          "foreign_key_column": null
        }
      },
      {
        "collection": "chiusella",
        "field": "additional_info",
        "type": "text",
        "meta": {
          "collection": "chiusella",
          "conditions": null,
          "display": null,
          "display_options": null,
          "field": "additional_info",
          "group": null,
          "hidden": false,
          "interface": "input-rich-text-html",
          "note": null,
          "options": null,
          "readonly": false,
          "required": false,
          "searchable": true,
          "sort": 16,
          "special": null,
          "translations": null,
          "validation": null,
          "validation_message": null,
          "width": "full"
        },
        "schema": {
          "name": "additional_info",
          "table": "chiusella",
          "data_type": "text",
          "default_value": null,
          "max_length": null,
          "numeric_precision": null,
          "numeric_scale": null,
          "is_nullable": true,
          "is_unique": false,
          "is_indexed": false,
          "is_primary_key": false,
          "is_generated": false,
          "generation_expression": null,
          "has_auto_increment": false,
          "foreign_key_table": null,
          "foreign_key_column": null
        }
      },
      {
        "collection": "chiusella_apartments",
        "field": "id",
        "type": "uuid",
        "meta": {
          "collection": "chiusella_apartments",
          "conditions": null,
          "display": null,
          "display_options": null,
          "field": "id",
          "group": null,
          "hidden": true,
          "interface": "input",
          "note": null,
          "options": null,
          "readonly": true,
          "required": false,
          "searchable": true,
          "sort": 1,
          "special": [
            "uuid"
          ],
          "translations": null,
          "validation": null,
          "validation_message": null,
          "width": "full"
        },
        "schema": {
          "name": "id",
          "table": "chiusella_apartments",
          "data_type": "uuid",
          "default_value": null,
          "max_length": null,
          "numeric_precision": null,
          "numeric_scale": null,
          "is_nullable": false,
          "is_unique": true,
          "is_indexed": false,
          "is_primary_key": true,
          "is_generated": false,
          "generation_expression": null,
          "has_auto_increment": false,
          "foreign_key_table": null,
          "foreign_key_column": null
        }
      },
      {
        "collection": "chiusella_apartments",
        "field": "apartment_name",
        "type": "string",
        "meta": {
          "collection": "chiusella_apartments",
          "conditions": null,
          "display": null,
          "display_options": {
            "prefix": "PRIV"
          },
          "field": "apartment_name",
          "group": null,
          "hidden": false,
          "interface": "input",
          "note": null,
          "options": null,
          "readonly": false,
          "required": false,
          "searchable": true,
          "sort": 2,
          "special": null,
          "translations": null,
          "validation": null,
          "validation_message": null,
          "width": "full"
        },
        "schema": {
          "name": "apartment_name",
          "table": "chiusella_apartments",
          "data_type": "character varying",
          "default_value": null,
          "max_length": 255,
          "numeric_precision": null,
          "numeric_scale": null,
          "is_nullable": true,
          "is_unique": false,
          "is_indexed": false,
          "is_primary_key": false,
          "is_generated": false,
          "generation_expression": null,
          "has_auto_increment": false,
          "foreign_key_table": null,
          "foreign_key_column": null
        }
      },
      {
        "collection": "chiusella_apartments",
        "field": "apartment_description",
        "type": "text",
        "meta": {
          "collection": "chiusella_apartments",
          "conditions": null,
          "display": null,
          "display_options": null,
          "field": "apartment_description",
          "group": null,
          "hidden": false,
          "interface": "input-rich-text-html",
          "note": null,
          "options": null,
          "readonly": false,
          "required": false,
          "searchable": true,
          "sort": 3,
          "special": null,
          "translations": null,
          "validation": null,
          "validation_message": null,
          "width": "full"
        },
        "schema": {
          "name": "apartment_description",
          "table": "chiusella_apartments",
          "data_type": "text",
          "default_value": null,
          "max_length": null,
          "numeric_precision": null,
          "numeric_scale": null,
          "is_nullable": true,
          "is_unique": false,
          "is_indexed": false,
          "is_primary_key": false,
          "is_generated": false,
          "generation_expression": null,
          "has_auto_increment": false,
          "foreign_key_table": null,
          "foreign_key_column": null
        }
      },
      {
        "collection": "chiusella_apartments",
        "field": "apartment_max_occupancy",
        "type": "integer",
        "meta": {
          "collection": "chiusella_apartments",
          "conditions": null,
          "display": null,
          "display_options": null,
          "field": "apartment_max_occupancy",
          "group": null,
          "hidden": false,
          "interface": "input",
          "note": null,
          "options": null,
          "readonly": false,
          "required": false,
          "searchable": true,
          "sort": 4,
          "special": null,
          "translations": null,
          "validation": null,
          "validation_message": null,
          "width": "full"
        },
        "schema": {
          "name": "apartment_max_occupancy",
          "table": "chiusella_apartments",
          "data_type": "integer",
          "default_value": null,
          "max_length": null,
          "numeric_precision": 32,
          "numeric_scale": 0,
          "is_nullable": true,
          "is_unique": false,
          "is_indexed": false,
          "is_primary_key": false,
          "is_generated": false,
          "generation_expression": null,
          "has_auto_increment": false,
          "foreign_key_table": null,
          "foreign_key_column": null
        }
      },
      {
        "collection": "chiusella_apartments",
        "field": "apartment_size_sqm",
        "type": "integer",
        "meta": {
          "collection": "chiusella_apartments",
          "conditions": null,
          "display": null,
          "display_options": null,
          "field": "apartment_size_sqm",
          "group": null,
          "hidden": false,
          "interface": "input",
          "note": null,
          "options": null,
          "readonly": false,
          "required": false,
          "searchable": true,
          "sort": 5,
          "special": null,
          "translations": null,
          "validation": null,
          "validation_message": null,
          "width": "full"
        },
        "schema": {
          "name": "apartment_size_sqm",
          "table": "chiusella_apartments",
          "data_type": "integer",
          "default_value": null,
          "max_length": null,
          "numeric_precision": 32,
          "numeric_scale": 0,
          "is_nullable": true,
          "is_unique": false,
          "is_indexed": false,
          "is_primary_key": false,
          "is_generated": false,
          "generation_expression": null,
          "has_auto_increment": false,
          "foreign_key_table": null,
          "foreign_key_column": null
        }
      },
      {
        "collection": "chiusella_apartments",
        "field": "apartment_floor",
        "type": "string",
        "meta": {
          "collection": "chiusella_apartments",
          "conditions": null,
          "display": null,
          "display_options": null,
          "field": "apartment_floor",
          "group": null,
          "hidden": false,
          "interface": "input",
          "note": null,
          "options": null,
          "readonly": false,
          "required": false,
          "searchable": true,
          "sort": 6,
          "special": null,
          "translations": null,
          "validation": null,
          "validation_message": null,
          "width": "full"
        },
        "schema": {
          "name": "apartment_floor",
          "table": "chiusella_apartments",
          "data_type": "character varying",
          "default_value": null,
          "max_length": 255,
          "numeric_precision": null,
          "numeric_scale": null,
          "is_nullable": true,
          "is_unique": false,
          "is_indexed": false,
          "is_primary_key": false,
          "is_generated": false,
          "generation_expression": null,
          "has_auto_increment": false,
          "foreign_key_table": null,
          "foreign_key_column": null
        }
      },
      {
        "collection": "chiusella_apartments",
        "field": "apartment_bedroom_count",
        "type": "integer",
        "meta": {
          "collection": "chiusella_apartments",
          "conditions": null,
          "display": null,
          "display_options": null,
          "field": "apartment_bedroom_count",
          "group": null,
          "hidden": false,
          "interface": "input",
          "note": null,
          "options": null,
          "readonly": false,
          "required": false,
          "searchable": true,
          "sort": 7,
          "special": null,
          "translations": null,
          "validation": null,
          "validation_message": null,
          "width": "full"
        },
        "schema": {
          "name": "apartment_bedroom_count",
          "table": "chiusella_apartments",
          "data_type": "integer",
          "default_value": null,
          "max_length": null,
          "numeric_precision": 32,
          "numeric_scale": 0,
          "is_nullable": true,
          "is_unique": false,
          "is_indexed": false,
          "is_primary_key": false,
          "is_generated": false,
          "generation_expression": null,
          "has_auto_increment": false,
          "foreign_key_table": null,
          "foreign_key_column": null
        }
      },
      {
        "collection": "chiusella_apartments",
        "field": "apartment_bed_details",
        "type": "string",
        "meta": {
          "collection": "chiusella_apartments",
          "conditions": null,
          "display": null,
          "display_options": null,
          "field": "apartment_bed_details",
          "group": null,
          "hidden": false,
          "interface": "input",
          "note": null,
          "options": null,
          "readonly": false,
          "required": false,
          "searchable": true,
          "sort": 8,
          "special": null,
          "translations": null,
          "validation": null,
          "validation_message": null,
          "width": "full"
        },
        "schema": {
          "name": "apartment_bed_details",
          "table": "chiusella_apartments",
          "data_type": "character varying",
          "default_value": null,
          "max_length": 255,
          "numeric_precision": null,
          "numeric_scale": null,
          "is_nullable": true,
          "is_unique": false,
          "is_indexed": false,
          "is_primary_key": false,
          "is_generated": false,
          "generation_expression": null,
          "has_auto_increment": false,
          "foreign_key_table": null,
          "foreign_key_column": null
        }
      },
      {
        "collection": "chiusella_apartments",
        "field": "apartment_bathroom_count",
        "type": "integer",
        "meta": {
          "collection": "chiusella_apartments",
          "conditions": null,
          "display": null,
          "display_options": null,
          "field": "apartment_bathroom_count",
          "group": null,
          "hidden": false,
          "interface": "input",
          "note": null,
          "options": null,
          "readonly": false,
          "required": false,
          "searchable": true,
          "sort": 9,
          "special": null,
          "translations": null,
          "validation": null,
          "validation_message": null,
          "width": "full"
        },
        "schema": {
          "name": "apartment_bathroom_count",
          "table": "chiusella_apartments",
          "data_type": "integer",
          "default_value": null,
          "max_length": null,
          "numeric_precision": 32,
          "numeric_scale": 0,
          "is_nullable": true,
          "is_unique": false,
          "is_indexed": false,
          "is_primary_key": false,
          "is_generated": false,
          "generation_expression": null,
          "has_auto_increment": false,
          "foreign_key_table": null,
          "foreign_key_column": null
        }
      },
      {
        "collection": "chiusella_apartments",
        "field": "apartment_has_kitchen",
        "type": "boolean",
        "meta": {
          "collection": "chiusella_apartments",
          "conditions": null,
          "display": null,
          "display_options": null,
          "field": "apartment_has_kitchen",
          "group": null,
          "hidden": false,
          "interface": "toggle",
          "note": null,
          "options": null,
          "readonly": false,
          "required": false,
          "searchable": true,
          "sort": 10,
          "special": null,
          "translations": null,
          "validation": null,
          "validation_message": null,
          "width": "full"
        },
        "schema": {
          "name": "apartment_has_kitchen",
          "table": "chiusella_apartments",
          "data_type": "boolean",
          "default_value": false,
          "max_length": null,
          "numeric_precision": null,
          "numeric_scale": null,
          "is_nullable": false,
          "is_unique": false,
          "is_indexed": false,
          "is_primary_key": false,
          "is_generated": false,
          "generation_expression": null,
          "has_auto_increment": false,
          "foreign_key_table": null,
          "foreign_key_column": null
        }
      },
      {
        "collection": "chiusella_apartments",
        "field": "apartment_kitchen_type",
        "type": "string",
        "meta": {
          "collection": "chiusella_apartments",
          "conditions": null,
          "display": null,
          "display_options": null,
          "field": "apartment_kitchen_type",
          "group": null,
          "hidden": false,
          "interface": "input",
          "note": null,
          "options": null,
          "readonly": false,
          "required": false,
          "searchable": true,
          "sort": 11,
          "special": null,
          "translations": null,
          "validation": null,
          "validation_message": null,
          "width": "full"
        },
        "schema": {
          "name": "apartment_kitchen_type",
          "table": "chiusella_apartments",
          "data_type": "character varying",
          "default_value": null,
          "max_length": 255,
          "numeric_precision": null,
          "numeric_scale": null,
          "is_nullable": true,
          "is_unique": false,
          "is_indexed": false,
          "is_primary_key": false,
          "is_generated": false,
          "generation_expression": null,
          "has_auto_increment": false,
          "foreign_key_table": null,
          "foreign_key_column": null
        }
      },
      {
        "collection": "chiusella_apartments",
        "field": "apartment_has_living_room",
        "type": "boolean",
        "meta": {
          "collection": "chiusella_apartments",
          "conditions": null,
          "display": null,
          "display_options": null,
          "field": "apartment_has_living_room",
          "group": null,
          "hidden": false,
          "interface": "toggle",
          "note": null,
          "options": null,
          "readonly": false,
          "required": false,
          "searchable": true,
          "sort": 12,
          "special": null,
          "translations": null,
          "validation": null,
          "validation_message": null,
          "width": "full"
        },
        "schema": {
          "name": "apartment_has_living_room",
          "table": "chiusella_apartments",
          "data_type": "boolean",
          "default_value": false,
          "max_length": null,
          "numeric_precision": null,
          "numeric_scale": null,
          "is_nullable": false,
          "is_unique": false,
          "is_indexed": false,
          "is_primary_key": false,
          "is_generated": false,
          "generation_expression": null,
          "has_auto_increment": false,
          "foreign_key_table": null,
          "foreign_key_column": null
        }
      },
      {
        "collection": "chiusella_apartments",
        "field": "apartment_has_fireplace",
        "type": "boolean",
        "meta": {
          "collection": "chiusella_apartments",
          "conditions": null,
          "display": null,
          "display_options": null,
          "field": "apartment_has_fireplace",
          "group": null,
          "hidden": false,
          "interface": "toggle",
          "note": null,
          "options": null,
          "readonly": false,
          "required": false,
          "searchable": true,
          "sort": 13,
          "special": null,
          "translations": null,
          "validation": null,
          "validation_message": null,
          "width": "full"
        },
        "schema": {
          "name": "apartment_has_fireplace",
          "table": "chiusella_apartments",
          "data_type": "boolean",
          "default_value": false,
          "max_length": null,
          "numeric_precision": null,
          "numeric_scale": null,
          "is_nullable": false,
          "is_unique": false,
          "is_indexed": false,
          "is_primary_key": false,
          "is_generated": false,
          "generation_expression": null,
          "has_auto_increment": false,
          "foreign_key_table": null,
          "foreign_key_column": null
        }
      },
      {
        "collection": "chiusella_apartments",
        "field": "apartment_has_balcony_veranda",
        "type": "boolean",
        "meta": {
          "collection": "chiusella_apartments",
          "conditions": null,
          "display": null,
          "display_options": null,
          "field": "apartment_has_balcony_veranda",
          "group": null,
          "hidden": false,
          "interface": "toggle",
          "note": null,
          "options": null,
          "readonly": false,
          "required": false,
          "searchable": true,
          "sort": 14,
          "special": null,
          "translations": null,
          "validation": null,
          "validation_message": null,
          "width": "full"
        },
        "schema": {
          "name": "apartment_has_balcony_veranda",
          "table": "chiusella_apartments",
          "data_type": "boolean",
          "default_value": false,
          "max_length": null,
          "numeric_precision": null,
          "numeric_scale": null,
          "is_nullable": false,
          "is_unique": false,
          "is_indexed": false,
          "is_primary_key": false,
          "is_generated": false,
          "generation_expression": null,
          "has_auto_increment": false,
          "foreign_key_table": null,
          "foreign_key_column": null
        }
      },
      {
        "collection": "chiusella_apartments",
        "field": "apartment_crib_available",
        "type": "boolean",
        "meta": {
          "collection": "chiusella_apartments",
          "conditions": null,
          "display": null,
          "display_options": null,
          "field": "apartment_crib_available",
          "group": null,
          "hidden": false,
          "interface": "toggle",
          "note": null,
          "options": null,
          "readonly": false,
          "required": false,
          "searchable": true,
          "sort": 15,
          "special": null,
          "translations": null,
          "validation": null,
          "validation_message": null,
          "width": "full"
        },
        "schema": {
          "name": "apartment_crib_available",
          "table": "chiusella_apartments",
          "data_type": "boolean",
          "default_value": false,
          "max_length": null,
          "numeric_precision": null,
          "numeric_scale": null,
          "is_nullable": false,
          "is_unique": false,
          "is_indexed": false,
          "is_primary_key": false,
          "is_generated": false,
          "generation_expression": null,
          "has_auto_increment": false,
          "foreign_key_table": null,
          "foreign_key_column": null
        }
      },
      {
        "collection": "chiusella_apartments",
        "field": "apartment_has_tv",
        "type": "boolean",
        "meta": {
          "collection": "chiusella_apartments",
          "conditions": null,
          "display": null,
          "display_options": null,
          "field": "apartment_has_tv",
          "group": null,
          "hidden": false,
          "interface": "toggle",
          "note": null,
          "options": null,
          "readonly": false,
          "required": false,
          "searchable": true,
          "sort": 16,
          "special": null,
          "translations": null,
          "validation": null,
          "validation_message": null,
          "width": "full"
        },
        "schema": {
          "name": "apartment_has_tv",
          "table": "chiusella_apartments",
          "data_type": "boolean",
          "default_value": false,
          "max_length": null,
          "numeric_precision": null,
          "numeric_scale": null,
          "is_nullable": false,
          "is_unique": false,
          "is_indexed": false,
          "is_primary_key": false,
          "is_generated": false,
          "generation_expression": null,
          "has_auto_increment": false,
          "foreign_key_table": null,
          "foreign_key_column": null
        }
      },
      {
        "collection": "chiusella_apartments",
        "field": "apartment_has_independent_heating",
        "type": "boolean",
        "meta": {
          "collection": "chiusella_apartments",
          "conditions": null,
          "display": null,
          "display_options": null,
          "field": "apartment_has_independent_heating",
          "group": null,
          "hidden": false,
          "interface": "toggle",
          "note": null,
          "options": null,
          "readonly": false,
          "required": false,
          "searchable": true,
          "sort": 17,
          "special": null,
          "translations": null,
          "validation": null,
          "validation_message": null,
          "width": "full"
        },
        "schema": {
          "name": "apartment_has_independent_heating",
          "table": "chiusella_apartments",
          "data_type": "boolean",
          "default_value": false,
          "max_length": null,
          "numeric_precision": null,
          "numeric_scale": null,
          "is_nullable": false,
          "is_unique": false,
          "is_indexed": false,
          "is_primary_key": false,
          "is_generated": false,
          "generation_expression": null,
          "has_auto_increment": false,
          "foreign_key_table": null,
          "foreign_key_column": null
        }
      },
      {
        "collection": "chiusella_apartments",
        "field": "apartment_has_air_conditioning",
        "type": "boolean",
        "meta": {
          "collection": "chiusella_apartments",
          "conditions": null,
          "display": null,
          "display_options": null,
          "field": "apartment_has_air_conditioning",
          "group": null,
          "hidden": false,
          "interface": "toggle",
          "note": null,
          "options": null,
          "readonly": false,
          "required": false,
          "searchable": true,
          "sort": 18,
          "special": null,
          "translations": null,
          "validation": null,
          "validation_message": null,
          "width": "full"
        },
        "schema": {
          "name": "apartment_has_air_conditioning",
          "table": "chiusella_apartments",
          "data_type": "boolean",
          "default_value": false,
          "max_length": null,
          "numeric_precision": null,
          "numeric_scale": null,
          "is_nullable": false,
          "is_unique": false,
          "is_indexed": false,
          "is_primary_key": false,
          "is_generated": false,
          "generation_expression": null,
          "has_auto_increment": false,
          "foreign_key_table": null,
          "foreign_key_column": null
        }
      },
      {
        "collection": "chiusella_apartments",
        "field": "apartment_has_wifi",
        "type": "boolean",
        "meta": {
          "collection": "chiusella_apartments",
          "conditions": null,
          "display": null,
          "display_options": null,
          "field": "apartment_has_wifi",
          "group": null,
          "hidden": false,
          "interface": "toggle",
          "note": null,
          "options": null,
          "readonly": false,
          "required": false,
          "searchable": true,
          "sort": 19,
          "special": null,
          "translations": null,
          "validation": null,
          "validation_message": null,
          "width": "full"
        },
        "schema": {
          "name": "apartment_has_wifi",
          "table": "chiusella_apartments",
          "data_type": "boolean",
          "default_value": false,
          "max_length": null,
          "numeric_precision": null,
          "numeric_scale": null,
          "is_nullable": false,
          "is_unique": false,
          "is_indexed": false,
          "is_primary_key": false,
          "is_generated": false,
          "generation_expression": null,
          "has_auto_increment": false,
          "foreign_key_table": null,
          "foreign_key_column": null
        }
      },
      {
        "collection": "chiusella_apartments",
        "field": "apartment_has_safe_box",
        "type": "boolean",
        "meta": {
          "collection": "chiusella_apartments",
          "conditions": null,
          "display": null,
          "display_options": null,
          "field": "apartment_has_safe_box",
          "group": null,
          "hidden": false,
          "interface": "toggle",
          "note": null,
          "options": null,
          "readonly": false,
          "required": false,
          "searchable": true,
          "sort": 20,
          "special": null,
          "translations": null,
          "validation": null,
          "validation_message": null,
          "width": "full"
        },
        "schema": {
          "name": "apartment_has_safe_box",
          "table": "chiusella_apartments",
          "data_type": "boolean",
          "default_value": false,
          "max_length": null,
          "numeric_precision": null,
          "numeric_scale": null,
          "is_nullable": false,
          "is_unique": false,
          "is_indexed": false,
          "is_primary_key": false,
          "is_generated": false,
          "generation_expression": null,
          "has_auto_increment": false,
          "foreign_key_table": null,
          "foreign_key_column": null
        }
      },
      {
        "collection": "chiusella_apartments",
        "field": "apartment_url",
        "type": "string",
        "meta": {
          "collection": "chiusella_apartments",
          "conditions": null,
          "display": null,
          "display_options": null,
          "field": "apartment_url",
          "group": null,
          "hidden": false,
          "interface": "input",
          "note": null,
          "options": null,
          "readonly": false,
          "required": false,
          "searchable": true,
          "sort": 21,
          "special": null,
          "translations": null,
          "validation": null,
          "validation_message": null,
          "width": "full"
        },
        "schema": {
          "name": "apartment_url",
          "table": "chiusella_apartments",
          "data_type": "character varying",
          "default_value": null,
          "max_length": 255,
          "numeric_precision": null,
          "numeric_scale": null,
          "is_nullable": true,
          "is_unique": false,
          "is_indexed": false,
          "is_primary_key": false,
          "is_generated": false,
          "generation_expression": null,
          "has_auto_increment": false,
          "foreign_key_table": null,
          "foreign_key_column": null
        }
      },
      {
        "collection": "chiusella_apartments",
        "field": "additional_info",
        "type": "text",
        "meta": {
          "collection": "chiusella_apartments",
          "conditions": null,
          "display": null,
          "display_options": null,
          "field": "additional_info",
          "group": null,
          "hidden": false,
          "interface": "input-rich-text-html",
          "note": null,
          "options": null,
          "readonly": false,
          "required": false,
          "searchable": true,
          "sort": 22,
          "special": null,
          "translations": null,
          "validation": null,
          "validation_message": null,
          "width": "full"
        },
        "schema": {
          "name": "additional_info",
          "table": "chiusella_apartments",
          "data_type": "text",
          "default_value": null,
          "max_length": null,
          "numeric_precision": null,
          "numeric_scale": null,
          "is_nullable": true,
          "is_unique": false,
          "is_indexed": false,
          "is_primary_key": false,
          "is_generated": false,
          "generation_expression": null,
          "has_auto_increment": false,
          "foreign_key_table": null,
          "foreign_key_column": null
        }
      },
      {
        "collection": "chiusella_experiences",
        "field": "id",
        "type": "uuid",
        "meta": {
          "collection": "chiusella_experiences",
          "conditions": null,
          "display": null,
          "display_options": null,
          "field": "id",
          "group": null,
          "hidden": true,
          "interface": "input",
          "note": null,
          "options": null,
          "readonly": true,
          "required": false,
          "searchable": true,
          "sort": 1,
          "special": [
            "uuid"
          ],
          "translations": null,
          "validation": null,
          "validation_message": null,
          "width": "full"
        },
        "schema": {
          "name": "id",
          "table": "chiusella_experiences",
          "data_type": "uuid",
          "default_value": null,
          "max_length": null,
          "numeric_precision": null,
          "numeric_scale": null,
          "is_nullable": false,
          "is_unique": true,
          "is_indexed": false,
          "is_primary_key": true,
          "is_generated": false,
          "generation_expression": null,
          "has_auto_increment": false,
          "foreign_key_table": null,
          "foreign_key_column": null
        }
      },
      {
        "collection": "chiusella_experiences",
        "field": "experience_name",
        "type": "string",
        "meta": {
          "collection": "chiusella_experiences",
          "conditions": null,
          "display": null,
          "display_options": null,
          "field": "experience_name",
          "group": null,
          "hidden": false,
          "interface": "input",
          "note": null,
          "options": null,
          "readonly": false,
          "required": false,
          "searchable": true,
          "sort": 2,
          "special": null,
          "translations": null,
          "validation": null,
          "validation_message": null,
          "width": "full"
        },
        "schema": {
          "name": "experience_name",
          "table": "chiusella_experiences",
          "data_type": "character varying",
          "default_value": null,
          "max_length": 255,
          "numeric_precision": null,
          "numeric_scale": null,
          "is_nullable": true,
          "is_unique": false,
          "is_indexed": false,
          "is_primary_key": false,
          "is_generated": false,
          "generation_expression": null,
          "has_auto_increment": false,
          "foreign_key_table": null,
          "foreign_key_column": null
        }
      },
      {
        "collection": "chiusella_experiences",
        "field": "experience_description",
        "type": "text",
        "meta": {
          "collection": "chiusella_experiences",
          "conditions": null,
          "display": null,
          "display_options": null,
          "field": "experience_description",
          "group": null,
          "hidden": false,
          "interface": "input-rich-text-html",
          "note": null,
          "options": null,
          "readonly": false,
          "required": false,
          "searchable": true,
          "sort": 3,
          "special": null,
          "translations": null,
          "validation": null,
          "validation_message": null,
          "width": "full"
        },
        "schema": {
          "name": "experience_description",
          "table": "chiusella_experiences",
          "data_type": "text",
          "default_value": null,
          "max_length": null,
          "numeric_precision": null,
          "numeric_scale": null,
          "is_nullable": true,
          "is_unique": false,
          "is_indexed": false,
          "is_primary_key": false,
          "is_generated": false,
          "generation_expression": null,
          "has_auto_increment": false,
          "foreign_key_table": null,
          "foreign_key_column": null
        }
      },
      {
        "collection": "chiusella_experiences",
        "field": "experience_category",
        "type": "string",
        "meta": {
          "collection": "chiusella_experiences",
          "conditions": null,
          "display": null,
          "display_options": null,
          "field": "experience_category",
          "group": null,
          "hidden": false,
          "interface": "input",
          "note": null,
          "options": null,
          "readonly": false,
          "required": false,
          "searchable": true,
          "sort": 4,
          "special": null,
          "translations": null,
          "validation": null,
          "validation_message": null,
          "width": "full"
        },
        "schema": {
          "name": "experience_category",
          "table": "chiusella_experiences",
          "data_type": "character varying",
          "default_value": null,
          "max_length": 255,
          "numeric_precision": null,
          "numeric_scale": null,
          "is_nullable": true,
          "is_unique": false,
          "is_indexed": false,
          "is_primary_key": false,
          "is_generated": false,
          "generation_expression": null,
          "has_auto_increment": false,
          "foreign_key_table": null,
          "foreign_key_column": null
        }
      },
      {
        "collection": "chiusella_experiences",
        "field": "experience_location",
        "type": "string",
        "meta": {
          "collection": "chiusella_experiences",
          "conditions": null,
          "display": null,
          "display_options": null,
          "field": "experience_location",
          "group": null,
          "hidden": false,
          "interface": "input",
          "note": null,
          "options": null,
          "readonly": false,
          "required": false,
          "searchable": true,
          "sort": 5,
          "special": null,
          "translations": null,
          "validation": null,
          "validation_message": null,
          "width": "full"
        },
        "schema": {
          "name": "experience_location",
          "table": "chiusella_experiences",
          "data_type": "character varying",
          "default_value": null,
          "max_length": 255,
          "numeric_precision": null,
          "numeric_scale": null,
          "is_nullable": true,
          "is_unique": false,
          "is_indexed": false,
          "is_primary_key": false,
          "is_generated": false,
          "generation_expression": null,
          "has_auto_increment": false,
          "foreign_key_table": null,
          "foreign_key_column": null
        }
      },
      {
        "collection": "chiusella_experiences",
        "field": "experience_distance_km",
        "type": "float",
        "meta": {
          "collection": "chiusella_experiences",
          "conditions": null,
          "display": null,
          "display_options": null,
          "field": "experience_distance_km",
          "group": null,
          "hidden": false,
          "interface": "input",
          "note": null,
          "options": null,
          "readonly": false,
          "required": false,
          "searchable": true,
          "sort": 6,
          "special": null,
          "translations": null,
          "validation": null,
          "validation_message": null,
          "width": "full"
        },
        "schema": {
          "name": "experience_distance_km",
          "table": "chiusella_experiences",
          "data_type": "real",
          "default_value": null,
          "max_length": null,
          "numeric_precision": 24,
          "numeric_scale": null,
          "is_nullable": true,
          "is_unique": false,
          "is_indexed": false,
          "is_primary_key": false,
          "is_generated": false,
          "generation_expression": null,
          "has_auto_increment": false,
          "foreign_key_table": null,
          "foreign_key_column": null
        }
      },
      {
        "collection": "chiusella_experiences",
        "field": "experience_suitable_for_families",
        "type": "boolean",
        "meta": {
          "collection": "chiusella_experiences",
          "conditions": null,
          "display": null,
          "display_options": null,
          "field": "experience_suitable_for_families",
          "group": null,
          "hidden": false,
          "interface": "toggle",
          "note": null,
          "options": null,
          "readonly": false,
          "required": false,
          "searchable": true,
          "sort": 7,
          "special": null,
          "translations": null,
          "validation": null,
          "validation_message": null,
          "width": "full"
        },
        "schema": {
          "name": "experience_suitable_for_families",
          "table": "chiusella_experiences",
          "data_type": "boolean",
          "default_value": null,
          "max_length": null,
          "numeric_precision": null,
          "numeric_scale": null,
          "is_nullable": false,
          "is_unique": false,
          "is_indexed": false,
          "is_primary_key": false,
          "is_generated": false,
          "generation_expression": null,
          "has_auto_increment": false,
          "foreign_key_table": null,
          "foreign_key_column": null
        }
      },
      {
        "collection": "chiusella_experiences",
        "field": "experience_url",
        "type": "string",
        "meta": {
          "collection": "chiusella_experiences",
          "conditions": null,
          "display": null,
          "display_options": null,
          "field": "experience_url",
          "group": null,
          "hidden": false,
          "interface": "input",
          "note": null,
          "options": null,
          "readonly": false,
          "required": false,
          "searchable": true,
          "sort": 8,
          "special": null,
          "translations": null,
          "validation": null,
          "validation_message": null,
          "width": "full"
        },
        "schema": {
          "name": "experience_url",
          "table": "chiusella_experiences",
          "data_type": "character varying",
          "default_value": null,
          "max_length": 255,
          "numeric_precision": null,
          "numeric_scale": null,
          "is_nullable": true,
          "is_unique": false,
          "is_indexed": false,
          "is_primary_key": false,
          "is_generated": false,
          "generation_expression": null,
          "has_auto_increment": false,
          "foreign_key_table": null,
          "foreign_key_column": null
        }
      },
      {
        "collection": "chiusella_experiences",
        "field": "additional_info",
        "type": "text",
        "meta": {
          "collection": "chiusella_experiences",
          "conditions": null,
          "display": "raw",
          "display_options": null,
          "field": "additional_info",
          "group": null,
          "hidden": false,
          "interface": "input-rich-text-html",
          "note": null,
          "options": null,
          "readonly": false,
          "required": false,
          "searchable": true,
          "sort": 9,
          "special": null,
          "translations": null,
          "validation": null,
          "validation_message": null,
          "width": "full"
        },
        "schema": {
          "name": "additional_info",
          "table": "chiusella_experiences",
          "data_type": "text",
          "default_value": null,
          "max_length": null,
          "numeric_precision": null,
          "numeric_scale": null,
          "is_nullable": true,
          "is_unique": false,
          "is_indexed": false,
          "is_primary_key": false,
          "is_generated": false,
          "generation_expression": null,
          "has_auto_increment": false,
          "foreign_key_table": null,
          "foreign_key_column": null
        }
      },
      {
        "collection": "chiusella_services",
        "field": "id",
        "type": "uuid",
        "meta": {
          "collection": "chiusella_services",
          "conditions": null,
          "display": null,
          "display_options": null,
          "field": "id",
          "group": null,
          "hidden": true,
          "interface": "input",
          "note": null,
          "options": null,
          "readonly": true,
          "required": false,
          "searchable": true,
          "sort": 1,
          "special": [
            "uuid"
          ],
          "translations": null,
          "validation": null,
          "validation_message": null,
          "width": "full"
        },
        "schema": {
          "name": "id",
          "table": "chiusella_services",
          "data_type": "uuid",
          "default_value": null,
          "max_length": null,
          "numeric_precision": null,
          "numeric_scale": null,
          "is_nullable": false,
          "is_unique": true,
          "is_indexed": false,
          "is_primary_key": true,
          "is_generated": false,
          "generation_expression": null,
          "has_auto_increment": false,
          "foreign_key_table": null,
          "foreign_key_column": null
        }
      },
      {
        "collection": "chiusella_services",
        "field": "additional_info",
        "type": "string",
        "meta": {
          "collection": "chiusella_services",
          "conditions": null,
          "display": null,
          "display_options": null,
          "field": "additional_info",
          "group": null,
          "hidden": false,
          "interface": "input",
          "note": null,
          "options": null,
          "readonly": false,
          "required": false,
          "searchable": true,
          "sort": 2,
          "special": null,
          "translations": null,
          "validation": null,
          "validation_message": null,
          "width": "full"
        },
        "schema": {
          "name": "additional_info",
          "table": "chiusella_services",
          "data_type": "character varying",
          "default_value": null,
          "max_length": 255,
          "numeric_precision": null,
          "numeric_scale": null,
          "is_nullable": true,
          "is_unique": false,
          "is_indexed": false,
          "is_primary_key": false,
          "is_generated": false,
          "generation_expression": null,
          "has_auto_increment": false,
          "foreign_key_table": null,
          "foreign_key_column": null
        }
      },
      {
        "collection": "chiusella_services",
        "field": "service_name",
        "type": "string",
        "meta": {
          "collection": "chiusella_services",
          "conditions": null,
          "display": null,
          "display_options": null,
          "field": "service_name",
          "group": null,
          "hidden": false,
          "interface": "input",
          "note": null,
          "options": null,
          "readonly": false,
          "required": false,
          "searchable": true,
          "sort": 3,
          "special": null,
          "translations": null,
          "validation": null,
          "validation_message": null,
          "width": "full"
        },
        "schema": {
          "name": "service_name",
          "table": "chiusella_services",
          "data_type": "character varying",
          "default_value": null,
          "max_length": 255,
          "numeric_precision": null,
          "numeric_scale": null,
          "is_nullable": true,
          "is_unique": false,
          "is_indexed": false,
          "is_primary_key": false,
          "is_generated": false,
          "generation_expression": null,
          "has_auto_increment": false,
          "foreign_key_table": null,
          "foreign_key_column": null
        }
      },
      {
        "collection": "chiusella_services",
        "field": "service_description",
        "type": "text",
        "meta": {
          "collection": "chiusella_services",
          "conditions": null,
          "display": null,
          "display_options": null,
          "field": "service_description",
          "group": null,
          "hidden": false,
          "interface": "input-rich-text-html",
          "note": null,
          "options": null,
          "readonly": false,
          "required": false,
          "searchable": true,
          "sort": 4,
          "special": null,
          "translations": null,
          "validation": null,
          "validation_message": null,
          "width": "full"
        },
        "schema": {
          "name": "service_description",
          "table": "chiusella_services",
          "data_type": "text",
          "default_value": null,
          "max_length": null,
          "numeric_precision": null,
          "numeric_scale": null,
          "is_nullable": true,
          "is_unique": false,
          "is_indexed": false,
          "is_primary_key": false,
          "is_generated": false,
          "generation_expression": null,
          "has_auto_increment": false,
          "foreign_key_table": null,
          "foreign_key_column": null
        }
      },
      {
        "collection": "chiusella_services",
        "field": "service_category",
        "type": "string",
        "meta": {
          "collection": "chiusella_services",
          "conditions": null,
          "display": null,
          "display_options": null,
          "field": "service_category",
          "group": null,
          "hidden": false,
          "interface": "input",
          "note": null,
          "options": null,
          "readonly": false,
          "required": false,
          "searchable": true,
          "sort": 5,
          "special": null,
          "translations": null,
          "validation": null,
          "validation_message": null,
          "width": "full"
        },
        "schema": {
          "name": "service_category",
          "table": "chiusella_services",
          "data_type": "character varying",
          "default_value": null,
          "max_length": 255,
          "numeric_precision": null,
          "numeric_scale": null,
          "is_nullable": true,
          "is_unique": false,
          "is_indexed": false,
          "is_primary_key": false,
          "is_generated": false,
          "generation_expression": null,
          "has_auto_increment": false,
          "foreign_key_table": null,
          "foreign_key_column": null
        }
      },
      {
        "collection": "chiusella_services",
        "field": "service_is_shared",
        "type": "boolean",
        "meta": {
          "collection": "chiusella_services",
          "conditions": null,
          "display": null,
          "display_options": null,
          "field": "service_is_shared",
          "group": null,
          "hidden": false,
          "interface": "toggle",
          "note": null,
          "options": null,
          "readonly": false,
          "required": false,
          "searchable": true,
          "sort": 6,
          "special": null,
          "translations": null,
          "validation": null,
          "validation_message": null,
          "width": "full"
        },
        "schema": {
          "name": "service_is_shared",
          "table": "chiusella_services",
          "data_type": "boolean",
          "default_value": false,
          "max_length": null,
          "numeric_precision": null,
          "numeric_scale": null,
          "is_nullable": false,
          "is_unique": false,
          "is_indexed": false,
          "is_primary_key": false,
          "is_generated": false,
          "generation_expression": null,
          "has_auto_increment": false,
          "foreign_key_table": null,
          "foreign_key_column": null
        }
      },
      {
        "collection": "chiusella_services",
        "field": "service_included",
        "type": "text",
        "meta": {
          "collection": "chiusella_services",
          "conditions": null,
          "display": null,
          "display_options": null,
          "field": "service_included",
          "group": null,
          "hidden": false,
          "interface": "input-rich-text-html",
          "note": null,
          "options": null,
          "readonly": false,
          "required": false,
          "searchable": true,
          "sort": 7,
          "special": null,
          "translations": null,
          "validation": null,
          "validation_message": null,
          "width": "full"
        },
        "schema": {
          "name": "service_included",
          "table": "chiusella_services",
          "data_type": "text",
          "default_value": null,
          "max_length": null,
          "numeric_precision": null,
          "numeric_scale": null,
          "is_nullable": true,
          "is_unique": false,
          "is_indexed": false,
          "is_primary_key": false,
          "is_generated": false,
          "generation_expression": null,
          "has_auto_increment": false,
          "foreign_key_table": null,
          "foreign_key_column": null
        }
      },
      {
        "collection": "chiusella_services",
        "field": "service_location",
        "type": "string",
        "meta": {
          "collection": "chiusella_services",
          "conditions": null,
          "display": null,
          "display_options": null,
          "field": "service_location",
          "group": null,
          "hidden": false,
          "interface": "input",
          "note": null,
          "options": null,
          "readonly": false,
          "required": false,
          "searchable": true,
          "sort": 8,
          "special": null,
          "translations": null,
          "validation": null,
          "validation_message": null,
          "width": "full"
        },
        "schema": {
          "name": "service_location",
          "table": "chiusella_services",
          "data_type": "character varying",
          "default_value": null,
          "max_length": 255,
          "numeric_precision": null,
          "numeric_scale": null,
          "is_nullable": true,
          "is_unique": false,
          "is_indexed": false,
          "is_primary_key": false,
          "is_generated": false,
          "generation_expression": null,
          "has_auto_increment": false,
          "foreign_key_table": null,
          "foreign_key_column": null
        }
      }
    ],
    "systemFields": [],
    "relations": []
  }
}